{
  "adding-home-screen.png": {
    "text": [
      "Copyright 2002-2016 University of Colorado Boulder"
    ],
    "projectURL": "http://phet.colorado.edu",
    "license": "contact phethelp@colorado.edu",
    "notes": "created by Amanda McGarry"
  },
  "adding-nav-bar.png": {
    "text": [
      "Copyright 2002-2016 University of Colorado Boulder"
    ],
    "projectURL": "http://phet.colorado.edu",
    "license": "contact phethelp@colorado.edu",
    "notes": "created by Amanda McGarry"
  },
  "explore-home-screen.png": {
    "text": [
      "Copyright 2002-2016 University of Colorado Boulder"
    ],
    "projectURL": "http://phet.colorado.edu",
    "license": "contact phethelp@colorado.edu",
    "notes": "created by Amanda McGarry"
  },
  "explore-nav-bar.png": {
    "text": [
      "Copyright 2002-2016 University of Colorado Boulder"
    ],
    "projectURL": "http://phet.colorado.edu",
    "license": "contact phethelp@colorado.edu",
    "notes": "created by Amanda McGarry"
  },
  "game-home-screen.png": {
    "text": [
      "Copyright 2002-2016 University of Colorado Boulder"
    ],
    "projectURL": "http://phet.colorado.edu",
    "license": "contact phethelp@colorado.edu",
    "notes": "created by Amanda McGarry"
  },
  "game-nav-bar.png": {
    "text": [
      "Copyright 2002-2016 University of Colorado Boulder"
    ],
    "projectURL": "http://phet.colorado.edu",
    "license": "contact phethelp@colorado.edu",
    "notes": "created by Amanda McGarry"
  },
  "level-1.png": {
    "text": [
      "Copyright 2002-2015 University of Colorado Boulder"
    ],
    "projectURL": "http://phet.colorado.edu",
    "license": "contact phethelp@colorado.edu",
    "notes": "created by Amanda McGarry"
  },
  "level-2.png": {
    "text": [
      "Copyright 2002-2015 University of Colorado Boulder"
    ],
    "projectURL": "http://phet.colorado.edu",
    "license": "contact phethelp@colorado.edu",
    "notes": "created by Amanda McGarry"
  },
  "level-3.png": {
    "text": [
      "Copyright 2002-2015 University of Colorado Boulder"
    ],
    "projectURL": "http://phet.colorado.edu",
    "license": "contact phethelp@colorado.edu",
    "notes": "created by Amanda McGarry"
  },
  "level-4.png": {
    "text": [
      "Copyright 2002-2015 University of Colorado Boulder"
    ],
    "projectURL": "http://phet.colorado.edu",
    "license": "contact phethelp@colorado.edu",
    "notes": "created by Amanda McGarry"
  },
  "level-5.png": {
    "text": [
      "Copyright 2002-2015 University of Colorado Boulder"
    ],
    "projectURL": "http://phet.colorado.edu",
    "license": "contact phethelp@colorado.edu",
    "notes": "created by Amanda McGarry"
  },
  "level-6.png": {
    "text": [
      "Copyright 2002-2015 University of Colorado Boulder"
    ],
    "projectURL": "http://phet.colorado.edu",
    "license": "contact phethelp@colorado.edu",
    "notes": "created by Amanda McGarry"
  },
  "level-7.png": {
    "text": [
      "Copyright 2002-2015 University of Colorado Boulder"
    ],
    "projectURL": "http://phet.colorado.edu",
    "license": "contact phethelp@colorado.edu",
    "notes": "created by Amanda McGarry"
  },
  "level-8.png": {
    "text": [
      "Copyright 2002-2015 University of Colorado Boulder"
    ],
    "projectURL": "http://phet.colorado.edu",
    "license": "contact phethelp@colorado.edu",
    "notes": "created by Amanda McGarry"
  },
  "level-9.png": {
    "text": [
      "Copyright 2002-2015 University of Colorado Boulder"
    ],
    "projectURL": "http://phet.colorado.edu",
    "license": "contact phethelp@colorado.edu",
    "notes": "created by Amanda McGarry"
  },
  "level-10.png": {
    "text": [
      "Copyright 2002-2015 University of Colorado Boulder"
    ],
    "projectURL": "http://phet.colorado.edu",
    "license": "contact phethelp@colorado.edu",
    "notes": "created by Amanda McGarry"
  },
  "1.png": {
    "text": [
      "Copyright 2002-2016 University of Colorado Boulder"
    ],
    "projectURL": "http://phet.colorado.edu",
    "license": "contact phethelp@colorado.edu",
    "notes": "created by Amanda McGarry, using a modified form of the Diggity (SIL Open Font License 1.1) font"
  },
  "10.png": {
    "text": [
      "Copyright 2002-2016 University of Colorado Boulder"
    ],
    "projectURL": "http://phet.colorado.edu",
    "license": "contact phethelp@colorado.edu",
    "notes": "created by Amanda McGarry, using a modified form of the Diggity (SIL Open Font License 1.1) font"
  },
  "100.png": {
    "text": [
      "Copyright 2002-2016 University of Colorado Boulder"
    ],
    "projectURL": "http://phet.colorado.edu",
    "license": "contact phethelp@colorado.edu",
    "notes": "created by Amanda McGarry, using a modified form of the Diggity (SIL Open Font License 1.1) font"
  },
  "2.png": {
    "text": [
      "Copyright 2002-2016 University of Colorado Boulder"
    ],
    "projectURL": "http://phet.colorado.edu",
    "license": "contact phethelp@colorado.edu",
    "notes": "created by Amanda McGarry, using a modified form of the Diggity (SIL Open Font License 1.1) font"
  },
  "20.png": {
    "text": [
      "Copyright 2002-2016 University of Colorado Boulder"
    ],
    "projectURL": "http://phet.colorado.edu",
    "license": "contact phethelp@colorado.edu",
    "notes": "created by Amanda McGarry, using a modified form of the Diggity (SIL Open Font License 1.1) font"
  },
  "200.png": {
    "text": [
      "Copyright 2002-2016 University of Colorado Boulder"
    ],
    "projectURL": "http://phet.colorado.edu",
    "license": "contact phethelp@colorado.edu",
    "notes": "created by Amanda McGarry, using a modified form of the Diggity (SIL Open Font License 1.1) font"
  },
  "3.png": {
    "text": [
      "Copyright 2002-2016 University of Colorado Boulder"
    ],
    "projectURL": "http://phet.colorado.edu",
    "license": "contact phethelp@colorado.edu",
    "notes": "created by Amanda McGarry, using a modified form of the Diggity (SIL Open Font License 1.1) font"
  },
  "30.png": {
    "text": [
      "Copyright 2002-2016 University of Colorado Boulder"
    ],
    "projectURL": "http://phet.colorado.edu",
    "license": "contact phethelp@colorado.edu",
    "notes": "created by Amanda McGarry, using a modified form of the Diggity (SIL Open Font License 1.1) font"
  },
  "300.png": {
    "text": [
      "Copyright 2002-2016 University of Colorado Boulder"
    ],
    "projectURL": "http://phet.colorado.edu",
    "license": "contact phethelp@colorado.edu",
    "notes": "created by Amanda McGarry, using a modified form of the Diggity (SIL Open Font License 1.1) font"
  },
  "4.png": {
    "text": [
      "Copyright 2002-2016 University of Colorado Boulder"
    ],
    "projectURL": "http://phet.colorado.edu",
    "license": "contact phethelp@colorado.edu",
    "notes": "created by Amanda McGarry, using a modified form of the Diggity (SIL Open Font License 1.1) font"
  },
  "40.png": {
    "text": [
      "Copyright 2002-2016 University of Colorado Boulder"
    ],
    "projectURL": "http://phet.colorado.edu",
    "license": "contact phethelp@colorado.edu",
    "notes": "created by Amanda McGarry, using a modified form of the Diggity (SIL Open Font License 1.1) font"
  },
  "400.png": {
    "text": [
      "Copyright 2002-2016 University of Colorado Boulder"
    ],
    "projectURL": "http://phet.colorado.edu",
    "license": "contact phethelp@colorado.edu",
    "notes": "created by Amanda McGarry, using a modified form of the Diggity (SIL Open Font License 1.1) font"
  },
  "5.png": {
    "text": [
      "Copyright 2002-2016 University of Colorado Boulder"
    ],
    "projectURL": "http://phet.colorado.edu",
    "license": "contact phethelp@colorado.edu",
    "notes": "created by Amanda McGarry, using a modified form of the Diggity (SIL Open Font License 1.1) font"
  },
  "50.png": {
    "text": [
      "Copyright 2002-2016 University of Colorado Boulder"
    ],
    "projectURL": "http://phet.colorado.edu",
    "license": "contact phethelp@colorado.edu",
    "notes": "created by Amanda McGarry, using a modified form of the Diggity (SIL Open Font License 1.1) font"
  },
  "500.png": {
    "text": [
      "Copyright 2002-2016 University of Colorado Boulder"
    ],
    "projectURL": "http://phet.colorado.edu",
    "license": "contact phethelp@colorado.edu",
    "notes": "created by Amanda McGarry, using a modified form of the Diggity (SIL Open Font License 1.1) font"
  },
  "6.png": {
    "text": [
      "Copyright 2002-2016 University of Colorado Boulder"
    ],
    "projectURL": "http://phet.colorado.edu",
    "license": "contact phethelp@colorado.edu",
    "notes": "created by Amanda McGarry, using a modified form of the Diggity (SIL Open Font License 1.1) font"
  },
  "60.png": {
    "text": [
      "Copyright 2002-2016 University of Colorado Boulder"
    ],
    "projectURL": "http://phet.colorado.edu",
    "license": "contact phethelp@colorado.edu",
    "notes": "created by Amanda McGarry, using a modified form of the Diggity (SIL Open Font License 1.1) font"
  },
  "600.png": {
    "text": [
      "Copyright 2002-2016 University of Colorado Boulder"
    ],
    "projectURL": "http://phet.colorado.edu",
    "license": "contact phethelp@colorado.edu",
    "notes": "created by Amanda McGarry, using a modified form of the Diggity (SIL Open Font License 1.1) font"
  },
  "7.png": {
    "text": [
      "Copyright 2002-2016 University of Colorado Boulder"
    ],
    "projectURL": "http://phet.colorado.edu",
    "license": "contact phethelp@colorado.edu",
    "notes": "created by Amanda McGarry, using a modified form of the Diggity (SIL Open Font License 1.1) font"
  },
  "70.png": {
    "text": [
      "Copyright 2002-2016 University of Colorado Boulder"
    ],
    "projectURL": "http://phet.colorado.edu",
    "license": "contact phethelp@colorado.edu",
    "notes": "created by Amanda McGarry, using a modified form of the Diggity (SIL Open Font License 1.1) font"
  },
  "700.png": {
    "text": [
      "Copyright 2002-2016 University of Colorado Boulder"
    ],
    "projectURL": "http://phet.colorado.edu",
    "license": "contact phethelp@colorado.edu",
    "notes": "created by Amanda McGarry, using a modified form of the Diggity (SIL Open Font License 1.1) font"
  },
  "8.png": {
    "text": [
      "Copyright 2002-2016 University of Colorado Boulder"
    ],
    "projectURL": "http://phet.colorado.edu",
    "license": "contact phethelp@colorado.edu",
    "notes": "created by Amanda McGarry, using a modified form of the Diggity (SIL Open Font License 1.1) font"
  },
  "80.png": {
    "text": [
      "Copyright 2002-2016 University of Colorado Boulder"
    ],
    "projectURL": "http://phet.colorado.edu",
    "license": "contact phethelp@colorado.edu",
    "notes": "created by Amanda McGarry, using a modified form of the Diggity (SIL Open Font License 1.1) font"
  },
  "800.png": {
    "text": [
      "Copyright 2002-2016 University of Colorado Boulder"
    ],
    "projectURL": "http://phet.colorado.edu",
    "license": "contact phethelp@colorado.edu",
    "notes": "created by Amanda McGarry, using a modified form of the Diggity (SIL Open Font License 1.1) font"
  },
  "9.png": {
    "text": [
      "Copyright 2002-2016 University of Colorado Boulder"
    ],
    "projectURL": "http://phet.colorado.edu",
    "license": "contact phethelp@colorado.edu",
    "notes": "created by Amanda McGarry, using a modified form of the Diggity (SIL Open Font License 1.1) font"
  },
  "90.png": {
    "text": [
      "Copyright 2002-2016 University of Colorado Boulder"
    ],
    "projectURL": "http://phet.colorado.edu",
    "license": "contact phethelp@colorado.edu",
    "notes": "created by Amanda McGarry, using a modified form of the Diggity (SIL Open Font License 1.1) font"
  },
  "900.png": {
    "text": [
      "Copyright 2002-2016 University of Colorado Boulder"
    ],
    "projectURL": "http://phet.colorado.edu",
    "license": "contact phethelp@colorado.edu",
    "notes": "created by Amanda McGarry, using a modified form of the Diggity (SIL Open Font License 1.1) font"
  },
  "1000.png": {
    "text": [
      "Copyright 2002-2016 University of Colorado Boulder"
    ],
    "projectURL": "http://phet.colorado.edu",
    "license": "contact phethelp@colorado.edu",
    "notes": "created by Amanda McGarry, using a modified form of the Diggity (SIL Open Font License 1.1) font"
  },
  "2000.png": {
    "text": [
      "Copyright 2002-2016 University of Colorado Boulder"
    ],
    "projectURL": "http://phet.colorado.edu",
    "license": "contact phethelp@colorado.edu",
    "notes": "created by Amanda McGarry, using a modified form of the Diggity (SIL Open Font License 1.1) font"
  },
  "3000.png": {
    "text": [
      "Copyright 2002-2016 University of Colorado Boulder"
    ],
    "projectURL": "http://phet.colorado.edu",
    "license": "contact phethelp@colorado.edu",
    "notes": "created by Amanda McGarry, using a modified form of the Diggity (SIL Open Font License 1.1) font"
  },
  "4000.png": {
    "text": [
      "Copyright 2002-2016 University of Colorado Boulder"
    ],
    "projectURL": "http://phet.colorado.edu",
    "license": "contact phethelp@colorado.edu",
    "notes": "created by Amanda McGarry, using a modified form of the Diggity (SIL Open Font License 1.1) font"
  },
  "5000.png": {
    "text": [
      "Copyright 2002-2016 University of Colorado Boulder"
    ],
    "projectURL": "http://phet.colorado.edu",
    "license": "contact phethelp@colorado.edu",
    "notes": "created by Amanda McGarry, using a modified form of the Diggity (SIL Open Font License 1.1) font"
  },
  "6000.png": {
    "text": [
      "Copyright 2002-2016 University of Colorado Boulder"
    ],
    "projectURL": "http://phet.colorado.edu",
    "license": "contact phethelp@colorado.edu",
    "notes": "created by Amanda McGarry, using a modified form of the Diggity (SIL Open Font License 1.1) font"
  },
  "7000.png": {
    "text": [
      "Copyright 2002-2016 University of Colorado Boulder"
    ],
    "projectURL": "http://phet.colorado.edu",
    "license": "contact phethelp@colorado.edu",
    "notes": "created by Amanda McGarry, using a modified form of the Diggity (SIL Open Font License 1.1) font"
  },
  "8000.png": {
    "text": [
      "Copyright 2002-2016 University of Colorado Boulder"
    ],
    "projectURL": "http://phet.colorado.edu",
    "license": "contact phethelp@colorado.edu",
    "notes": "created by Amanda McGarry, using a modified form of the Diggity (SIL Open Font License 1.1) font"
  },
  "9000.png": {
    "text": [
      "Copyright 2002-2016 University of Colorado Boulder"
    ],
    "projectURL": "http://phet.colorado.edu",
    "license": "contact phethelp@colorado.edu",
    "notes": "created by Amanda McGarry, using a modified form of the Diggity (SIL Open Font License 1.1) font"
  },
  "edit.png": {
    "text": [
      "Copyright 2002-2015 University of Colorado Boulder"
    ],
    "projectURL": "http://phet.colorado.edu",
    "license": "contact phethelp@colorado.edu",
    "notes": ""
  }
}